{
    "patent_id": "US-11013425-B2",
    "title": "Systems and methods for analyzing and processing digital images to estimate vessel characteristics ",
    "assignee": "Heartflow, Inc.",
    "publication_date": "2021-05-25",
    "patent_link": "https://patents.google.com/patent/US11013425B2/en",
    "inventors": [
        "Timothy A. Fonte",
        "Gilwoo Choi",
        "Leo Grady",
        "Michael Singer"
    ],
    "classifications": [
        "A61B6/504",
        "A61B5/026",
        "A61B5/0022",
        "A61B5/02007",
        "A61B5/0205",
        "A61B5/021",
        "A61B5/107",
        "A61B5/14535",
        "A61B5/14546",
        "A61B5/7267",
        "A61B5/7278",
        "A61B5/7282",
        "A61B5/742",
        "A61B5/743",
        "A61B6/032",
        "A61B6/463",
        "A61B6/507",
        "A61B6/5217",
        "A61B6/563",
        "G06N20/00",
        "G06N7/005",
        "G06N7/01",
        "G16H50/20",
        "A61B2560/0475",
        "A61B5/024"
    ],
    "abstract": "Systems and methods are disclosed for determining individual-specific blood flow characteristics. One method includes acquiring, for each of a plurality of individuals, individual-specific anatomic data and blood flow characteristics of at least part of the individual's vascular system; executing a machine learning algorithm on the individual-specific anatomic data and blood flow characteristics for each of the plurality of individuals; relating, based on the executed machine learning algorithm, each individual's individual-specific anatomic data to functional estimates of blood flow characteristics; acquiring, for an individual and individual-specific anatomic data of at least part of the individual's vascular system; and for at least one point in the individual's individual-specific anatomic data, determining a blood flow characteristic of the individual, using relations from the step of relating individual-specific anatomic data to functional estimates of blood flow characteristics.",
    "claims": "\n1. A method for personalized non-invasive assessment of artery stenosis for a patient, comprising:\nreceiving medical image data of at least a part of the patient's vascular system including one or more arteries of the patient;\nextracting patient-specific arterial geometry of the patient from the received medical image data;\nextracting features from the patient-specific arterial geometry of the patient, the extracted features corresponding to features of a trained machine-learning based model for predicting physiologic values based on learned associations between the physiologic values and the extracted features; and\nautomatically computing one or more index values of the physiologic values for one or more locations of interest in the patient-specific arterial geometry based on the extracted features using the trained machine-learning based model trained based on features extracted from one or both of anatomical features extracted from individuals other than the patient and synthetically generated arterial geometries, based on the learned associations between the physiologic values and the extracted features.\n2. The method of claim 1, further comprising:\nreceiving at least one of non-invasive physiological measurements of the patient or demographic data of the patient,\nwherein computing the one or more index values is further based on features corresponding to the at least one of the non-invasive physiological measurements of the patient or the demographic data of the patient.\n3. The method of claim 1, further comprising\nreceiving one or more biomarkers of the patient,\nwherein computing the one or more index values is further based on features corresponding to the one or more biomarkers of the patient.\n4. The method of claim 1, wherein the physiologic values are physiologic blood pressure values, and the trained machine-learning based model is trained based on one or more patient-specific models of blood flow circulation.\n5. The method of claim 1, wherein extracting features from the patient-specific arterial geometry of the patient further comprises:\nextracting a plurality of geometric measurements for one or more artery stenosis regions in the patient-specific arterial geometry of the patient.\n6. The method of claim 1, wherein the one or more locations of interest correspond to one or more artery stenosis locations.\n7. The method of claim 1, wherein computing the one or more index values for one or more locations of interest in the patient-specific arterial geometry is in response to a user input identifying the one or more locations of interest.\n8. The method of claim 1, wherein the physiologic values are physiologic blood pressure values and the one or more index values are one or more fractional flow reserve (FFR) values.\n9. The method of claim 1, wherein computing the one or more index values comprises:\ncomputing a plurality of hemodynamic indices of the physiologic values for each of the one or more locations of interest in the patient-specific arterial geometry based on the extracted features using a respective one of a plurality of trained machine-learning based models trained based on the features extracted from the one or both of anatomical features extracted from individuals other the patient and/or synthetically generated arterial geometries, based on the learned associations between physiologic values and the extracted features.\n10. The method of claim 1, further comprising: displaying a visualization of the patient-specific arterial geometry color coded based on the one or more index values computed for the one or more locations of interest in the patient-specific arterial geometry.\n11. A system for personalized non-invasive assessment of artery stenosis for a patient, comprising:\nat least one data storage device storing instructions for personalized non-invasive assessment of artery stenosis for a patient in an electronic storage medium; and\nat least one processor configured to execute the instructions to perform operations comprising:\nreceiving medical image data of at least a part of the patient's vascular system including one or more arteries of the patient;\nextracting patient-specific arterial geometry of the patient from the received medical image data;\nextracting features from the patient-specific arterial geometry of the patient, the extracted features corresponding to features of a trained machine-learning based model for predicting physiologic values based on learned associations between the physiologic values and the extracted features; and\nautomatically computing one or more index values of the physiologic values for one or more locations of interest in the patient-specific arterial geometry based on the extracted features using the trained machine-learning based model trained based on features extracted from one or both of anatomical features extracted from individuals other than the patient and synthetically generated arterial geometries, based on the learned associations between the physiologic values and the extracted features.\n12. The system of claim 11, the operations further comprising:\nreceiving at least one of non-invasive physiological measurements of the patient or demographic data of the patient,\nwherein computing the one or more index values is further based on based on features corresponding to at least one of the non-invasive physiological measurements of the patient or the demographic data of the patient using the trained machine-learning based model.\n13. The system of claim 11, the operations further comprising:\nreceiving one or more biomarkers of the patient,\nwherein computing the one or more index values is further based on features corresponding to one or more biomarkers of the patient using the trained machine-learning based model.\n14. The system of claim 11, wherein the physiologic values are physiologic blood pressure values, and the trained machine-learning based model is trained based on one or more patient-specific multi-scale models of blood flow circulation.\n15. The system of claim 11, wherein the physiologic values are physiologic blood pressure values, the one or more index values are one or more fractional flow reserve (FFR) values.\n16. The system of claim 11, wherein computing the one or more index values comprises:\ncomputing a plurality of hemodynamic indices of the physiologic values for each of the one or more locations of interest in the patient-specific arterial geometry based on the extracted features using a respective one of a plurality of trained machine-learning based models trained based on the features extracted from the one or both of anatomical features extracted from individuals other the patient and/or synthetically generated arterial geometries, based on the learned associations between physiologic values and the extracted features.\n17. The system of claim 11, further comprising: displaying a visualization of the patient-specific arterial geometry color coded based on the one or more index values computed for the one or more locations of interest in the patient-specific arterial geometry.\n18. A non-transitory computer readable medium, for personalized non-invasive assessment of artery stenosis for a patient, storing operations comprising:\nreceiving medical image data of at least a part of the patient's vascular system including one or more arteries of the patient;\nextracting patient-specific arterial geometry of the patient from the received medical image data;\nextracting features from the patient-specific arterial geometry of the patient, the extracted features corresponding to features of a trained machine-learning based model for predicting physiologic values based on learned associations between the physiologic values and the extracted features; and\nautomatically computing one or more index values of the physiologic values for one or more locations of interest in the patient-specific arterial geometry based on the extracted features using the trained machine-learning based model trained based on features extracted from one or both of anatomical features extracted from individuals other than the patient and synthetically generated arterial geometries, based on the learned associations between the physiologic values and the extracted features.\n19. The computer-readable medium of claim 18, the operations further comprising:\nreceiving at least one of non-invasive physiological measurements of the patient or demographic data of the patient,\nwherein computing the one or more index values is further based on based on features corresponding to at least one of the non-invasive physiological measurements of the patient or the demographic data of the patient using the trained machine-learning based model.\n20. The computer-readable medium of claim 18, the operations further comprising:\nreceiving one or more biomarkers of the patient,\nwherein computing the one or more index values is further based on features corresponding to one or more biomarkers of the patient using the trained machine-learning based model.",
    "status": "Active",
    "citations_own": [
        "JPH01145043A",
        "JPH0824227A",
        "US5533511A",
        "US6377832B1",
        "US20030004652A1",
        "US20030087244A1",
        "WO2005001769A2",
        "US20080292049A1",
        "US20090080745A1",
        "US20090103794A1",
        "WO2011015822A1",
        "US20110060576A1",
        "US20110071404A1",
        "US20110282169A1",
        "US20120022843A1",
        "JP2012024582A",
        "US20120041318A1",
        "US20120053918A1",
        "US20120072190A1",
        "US20120142632A1",
        "US20120201446A1",
        "JP2012159990A",
        "US20120232853A1",
        "US20130132054A1",
        "US20130197884A1",
        "US20130246034A1",
        "US20130243294A1",
        "US20140073976A1",
        "US8684921B2",
        "US20140100451A1",
        "US20140121513A1",
        "US20140220580A1",
        "US8821408B2",
        "US20140249784A1",
        "US20150042646A1",
        "US20150112182A1",
        "US20150282765A1",
        "JP2016028747A",
        "US9349178B1",
        "US20160166209A1",
        "US20170014033A1",
        "JP2017512577A"
    ],
    "citations_ftf": [
        "US7604472B2",
        "US20120316421A1",
        "US20110081057A1",
        "GB201100137D0",
        "US9805463B2",
        "US9888968B2",
        "US11087459B2",
        "CN113440112A",
        "US20200085382A1",
        "US10650286B2",
        "US10363008B2",
        "US10699407B2"
    ],
    "citedby_own": [
        "US11113811B2",
        "US11210786B2",
        "US11317883B2"
    ],
    "citedby_ftf": [
        "ES2832713T3",
        "US8781555B2",
        "US9521961B2",
        "US8200466B2",
        "US9405886B2",
        "US9532724B2",
        "EP2575611B1",
        "US8315812B2",
        "US10433740B2",
        "US10398386B2",
        "US9135381B2",
        "US9805463B2",
        "US9668699B2",
        "US9700219B2",
        "US9730643B2",
        "US9092743B2",
        "US9501622B2",
        "US9087147B1",
        "EP3160335B1",
        "US9390224B2",
        "EP3192051B1",
        "US9594876B2",
        "US9336354B1",
        "US10080872B2",
        "EP3218872A2",
        "US9349178B1",
        "WO2016075331A2",
        "US10595790B2",
        "US20160203289A1",
        "US20160224753A1",
        "WO2016161308A1",
        "CN107615335A",
        "US11147505B1",
        "US10872698B2",
        "US11094058B2",
        "US11071501B2",
        "US11087459B2",
        "US10176408B2",
        "US11676359B2",
        "US11113812B2",
        "TWI545516B",
        "US10492754B2",
        "US11191490B2",
        "CN105326486B",
        "WO2017187269A1",
        "US20170322684A1",
        "CN106073894B",
        "US11020563B2",
        "US11039804B2",
        "DE102016222102A1",
        "EP3270355B1",
        "US10176896B2",
        "JP7300392B2",
        "EP3404667A1",
        "US10483006B2",
        "EP3270308B9",
        "JP6964769B2",
        "US11633118B2",
        "EP3437559B1",
        "US10679384B2",
        "US10762637B2",
        "US10522253B2",
        "EP3488774A1",
        "CN108511075B",
        "CN109065170B",
        "CN108777174B",
        "CN108784676B",
        "CN108742586B",
        "CN108717874B",
        "CN109033219B",
        "CN112867443A",
        "CN111227821B",
        "US10964017B2",
        "US11227418B2",
        "US20220093267A1",
        "CN111476791A",
        "CN110279404B",
        "CN110522465A",
        "EP4004946A4",
        "US11508063B2",
        "US11759166B2",
        "US11416360B2",
        "US20230103319A1",
        "US20230190113A1",
        "US20230263493A1",
        "CN113100737B",
        "US11694807B2"
    ]
}